<?xml version="1.0" encoding="UTF-8"?>
<!DOCTYPE mapper PUBLIC "-//mybatis.org//DTD Mapper 3.0//EN" "http://mybatis.org/dtd/mybatis-3-mapper.dtd">
<mapper namespace="com.bruce.geekway.dao.mapper.ProductMapper">
  <resultMap id="BaseResultMap" type="com.bruce.geekway.model.Product">
    <!--
      WARNING - @mbggenerated
      This element is automatically generated by MyBatis Generator, do not modify.
      This element was generated on Tue Jan 13 16:05:27 CST 2015.
    -->
    <id column="id" jdbcType="INTEGER" property="id" />
    <result column="sku_category_id" jdbcType="INTEGER" property="skuCategoryId" />
    <result column="category_id" jdbcType="INTEGER" property="categoryId" />
    <result column="out_id" jdbcType="VARCHAR" property="outId" />
    <result column="name" jdbcType="VARCHAR" property="name" />
    <result column="description" jdbcType="VARCHAR" property="description" />
    <result column="param" jdbcType="VARCHAR" property="param" />
    <result column="stock" jdbcType="INTEGER" property="stock" />
    <result column="origin_price" jdbcType="DOUBLE" property="originPrice" />
    <result column="price" jdbcType="DOUBLE" property="price" />
    <result column="cover_pic_url" jdbcType="VARCHAR" property="coverPicUrl" />
    <result column="wx_share_title" jdbcType="VARCHAR" property="wxShareTitle" />
    <result column="wx_share_content" jdbcType="VARCHAR" property="wxShareContent" />
    <result column="wx_share_icon_url" jdbcType="VARCHAR" property="wxShareIconUrl" />
    <result column="status" jdbcType="SMALLINT" property="status" />
    <result column="create_time" jdbcType="TIMESTAMP" property="createTime" />
    <result column="update_time" jdbcType="TIMESTAMP" property="updateTime" />
  </resultMap>
  <sql id="Example_Where_Clause">
    <!--
      WARNING - @mbggenerated
      This element is automatically generated by MyBatis Generator, do not modify.
      This element was generated on Tue Jan 13 16:05:27 CST 2015.
    -->
    <where>
      <foreach collection="oredCriteria" item="criteria" separator="or">
        <if test="criteria.valid">
          <trim prefix="(" prefixOverrides="and" suffix=")">
            <foreach collection="criteria.criteria" item="criterion">
              <choose>
                <when test="criterion.noValue">
                  and ${criterion.condition}
                </when>
                <when test="criterion.singleValue">
                  and ${criterion.condition} #{criterion.value}
                </when>
                <when test="criterion.betweenValue">
                  and ${criterion.condition} #{criterion.value} and #{criterion.secondValue}
                </when>
                <when test="criterion.listValue">
                  and ${criterion.condition}
                  <foreach close=")" collection="criterion.value" item="listItem" open="(" separator=",">
                    #{listItem}
                  </foreach>
                </when>
              </choose>
            </foreach>
          </trim>
        </if>
      </foreach>
    </where>
  </sql>
  <sql id="Update_By_Example_Where_Clause">
    <!--
      WARNING - @mbggenerated
      This element is automatically generated by MyBatis Generator, do not modify.
      This element was generated on Tue Jan 13 16:05:27 CST 2015.
    -->
    <where>
      <foreach collection="example.oredCriteria" item="criteria" separator="or">
        <if test="criteria.valid">
          <trim prefix="(" prefixOverrides="and" suffix=")">
            <foreach collection="criteria.criteria" item="criterion">
              <choose>
                <when test="criterion.noValue">
                  and ${criterion.condition}
                </when>
                <when test="criterion.singleValue">
                  and ${criterion.condition} #{criterion.value}
                </when>
                <when test="criterion.betweenValue">
                  and ${criterion.condition} #{criterion.value} and #{criterion.secondValue}
                </when>
                <when test="criterion.listValue">
                  and ${criterion.condition}
                  <foreach close=")" collection="criterion.value" item="listItem" open="(" separator=",">
                    #{listItem}
                  </foreach>
                </when>
              </choose>
            </foreach>
          </trim>
        </if>
      </foreach>
    </where>
  </sql>
  <sql id="Base_Column_List">
    <!--
      WARNING - @mbggenerated
      This element is automatically generated by MyBatis Generator, do not modify.
      This element was generated on Tue Jan 13 16:05:27 CST 2015.
    -->
    id, sku_category_id, category_id, out_id, name, description, param, stock, origin_price, 
    price, cover_pic_url, wx_share_title, wx_share_content, wx_share_icon_url, status, 
    create_time, update_time
  </sql>
  <select id="selectByExample" parameterType="com.bruce.geekway.model.ProductCriteria" resultMap="BaseResultMap">
    <!--
      WARNING - @mbggenerated
      This element is automatically generated by MyBatis Generator, do not modify.
      This element was generated on Tue Jan 13 16:05:27 CST 2015.
    -->
    select
    <if test="distinct">
      distinct
    </if>
    <include refid="Base_Column_List" />
    from tb_product
    <if test="_parameter != null">
      <include refid="Example_Where_Clause" />
    </if>
    <if test="orderByClause != null">
      order by ${orderByClause}
    </if>
    <if test="limitRows != null">
      limit 
      <if test="limitOffset != null">
        #{limitOffset}, 
      </if>
      #{limitRows}
    </if>
  </select>
  <select id="selectByPrimaryKey" parameterType="java.lang.Integer" resultMap="BaseResultMap">
    <!--
      WARNING - @mbggenerated
      This element is automatically generated by MyBatis Generator, do not modify.
      This element was generated on Tue Jan 13 16:05:27 CST 2015.
    -->
    select 
    <include refid="Base_Column_List" />
    from tb_product
    where id = #{id,jdbcType=INTEGER}
  </select>
  <delete id="deleteByPrimaryKey" parameterType="java.lang.Integer">
    <!--
      WARNING - @mbggenerated
      This element is automatically generated by MyBatis Generator, do not modify.
      This element was generated on Tue Jan 13 16:05:27 CST 2015.
    -->
    delete from tb_product
    where id = #{id,jdbcType=INTEGER}
  </delete>
  <delete id="deleteByExample" parameterType="com.bruce.geekway.model.ProductCriteria">
    <!--
      WARNING - @mbggenerated
      This element is automatically generated by MyBatis Generator, do not modify.
      This element was generated on Tue Jan 13 16:05:27 CST 2015.
    -->
    delete from tb_product
    <if test="_parameter != null">
      <include refid="Example_Where_Clause" />
    </if>
  </delete>
  <insert id="insert" keyProperty="id" parameterType="com.bruce.geekway.model.Product" useGeneratedKeys="true">
    <!--
      WARNING - @mbggenerated
      This element is automatically generated by MyBatis Generator, do not modify.
      This element was generated on Tue Jan 13 16:05:27 CST 2015.
    -->
    insert into tb_product (id, sku_category_id, category_id, 
      out_id, name, description, 
      param, stock, origin_price, 
      price, cover_pic_url, wx_share_title, 
      wx_share_content, wx_share_icon_url, status, 
      create_time, update_time)
    values (#{id,jdbcType=INTEGER}, #{skuCategoryId,jdbcType=INTEGER}, #{categoryId,jdbcType=INTEGER}, 
      #{outId,jdbcType=VARCHAR}, #{name,jdbcType=VARCHAR}, #{description,jdbcType=VARCHAR}, 
      #{param,jdbcType=VARCHAR}, #{stock,jdbcType=INTEGER}, #{originPrice,jdbcType=DOUBLE}, 
      #{price,jdbcType=DOUBLE}, #{coverPicUrl,jdbcType=VARCHAR}, #{wxShareTitle,jdbcType=VARCHAR}, 
      #{wxShareContent,jdbcType=VARCHAR}, #{wxShareIconUrl,jdbcType=VARCHAR}, #{status,jdbcType=SMALLINT}, 
      #{createTime,jdbcType=TIMESTAMP}, #{updateTime,jdbcType=TIMESTAMP})
  </insert>
  <insert id="insertSelective" keyProperty="id" parameterType="com.bruce.geekway.model.Product" useGeneratedKeys="true">
    <!--
      WARNING - @mbggenerated
      This element is automatically generated by MyBatis Generator, do not modify.
      This element was generated on Tue Jan 13 16:05:27 CST 2015.
    -->
    insert into tb_product
    <trim prefix="(" suffix=")" suffixOverrides=",">
      <if test="id != null">
        id,
      </if>
      <if test="skuCategoryId != null">
        sku_category_id,
      </if>
      <if test="categoryId != null">
        category_id,
      </if>
      <if test="outId != null">
        out_id,
      </if>
      <if test="name != null">
        name,
      </if>
      <if test="description != null">
        description,
      </if>
      <if test="param != null">
        param,
      </if>
      <if test="stock != null">
        stock,
      </if>
      <if test="originPrice != null">
        origin_price,
      </if>
      <if test="price != null">
        price,
      </if>
      <if test="coverPicUrl != null">
        cover_pic_url,
      </if>
      <if test="wxShareTitle != null">
        wx_share_title,
      </if>
      <if test="wxShareContent != null">
        wx_share_content,
      </if>
      <if test="wxShareIconUrl != null">
        wx_share_icon_url,
      </if>
      <if test="status != null">
        status,
      </if>
      <if test="createTime != null">
        create_time,
      </if>
      <if test="updateTime != null">
        update_time,
      </if>
    </trim>
    <trim prefix="values (" suffix=")" suffixOverrides=",">
      <if test="id != null">
        #{id,jdbcType=INTEGER},
      </if>
      <if test="skuCategoryId != null">
        #{skuCategoryId,jdbcType=INTEGER},
      </if>
      <if test="categoryId != null">
        #{categoryId,jdbcType=INTEGER},
      </if>
      <if test="outId != null">
        #{outId,jdbcType=VARCHAR},
      </if>
      <if test="name != null">
        #{name,jdbcType=VARCHAR},
      </if>
      <if test="description != null">
        #{description,jdbcType=VARCHAR},
      </if>
      <if test="param != null">
        #{param,jdbcType=VARCHAR},
      </if>
      <if test="stock != null">
        #{stock,jdbcType=INTEGER},
      </if>
      <if test="originPrice != null">
        #{originPrice,jdbcType=DOUBLE},
      </if>
      <if test="price != null">
        #{price,jdbcType=DOUBLE},
      </if>
      <if test="coverPicUrl != null">
        #{coverPicUrl,jdbcType=VARCHAR},
      </if>
      <if test="wxShareTitle != null">
        #{wxShareTitle,jdbcType=VARCHAR},
      </if>
      <if test="wxShareContent != null">
        #{wxShareContent,jdbcType=VARCHAR},
      </if>
      <if test="wxShareIconUrl != null">
        #{wxShareIconUrl,jdbcType=VARCHAR},
      </if>
      <if test="status != null">
        #{status,jdbcType=SMALLINT},
      </if>
      <if test="createTime != null">
        #{createTime,jdbcType=TIMESTAMP},
      </if>
      <if test="updateTime != null">
        #{updateTime,jdbcType=TIMESTAMP},
      </if>
    </trim>
  </insert>
  <select id="countByExample" parameterType="com.bruce.geekway.model.ProductCriteria" resultType="java.lang.Integer">
    <!--
      WARNING - @mbggenerated
      This element is automatically generated by MyBatis Generator, do not modify.
      This element was generated on Tue Jan 13 16:05:27 CST 2015.
    -->
    select count(*) from tb_product
    <if test="_parameter != null">
      <include refid="Example_Where_Clause" />
    </if>
  </select>
  <update id="updateByExampleSelective" parameterType="map">
    <!--
      WARNING - @mbggenerated
      This element is automatically generated by MyBatis Generator, do not modify.
      This element was generated on Tue Jan 13 16:05:27 CST 2015.
    -->
    update tb_product
    <set>
      <if test="record.id != null">
        id = #{record.id,jdbcType=INTEGER},
      </if>
      <if test="record.skuCategoryId != null">
        sku_category_id = #{record.skuCategoryId,jdbcType=INTEGER},
      </if>
      <if test="record.categoryId != null">
        category_id = #{record.categoryId,jdbcType=INTEGER},
      </if>
      <if test="record.outId != null">
        out_id = #{record.outId,jdbcType=VARCHAR},
      </if>
      <if test="record.name != null">
        name = #{record.name,jdbcType=VARCHAR},
      </if>
      <if test="record.description != null">
        description = #{record.description,jdbcType=VARCHAR},
      </if>
      <if test="record.param != null">
        param = #{record.param,jdbcType=VARCHAR},
      </if>
      <if test="record.stock != null">
        stock = #{record.stock,jdbcType=INTEGER},
      </if>
      <if test="record.originPrice != null">
        origin_price = #{record.originPrice,jdbcType=DOUBLE},
      </if>
      <if test="record.price != null">
        price = #{record.price,jdbcType=DOUBLE},
      </if>
      <if test="record.coverPicUrl != null">
        cover_pic_url = #{record.coverPicUrl,jdbcType=VARCHAR},
      </if>
      <if test="record.wxShareTitle != null">
        wx_share_title = #{record.wxShareTitle,jdbcType=VARCHAR},
      </if>
      <if test="record.wxShareContent != null">
        wx_share_content = #{record.wxShareContent,jdbcType=VARCHAR},
      </if>
      <if test="record.wxShareIconUrl != null">
        wx_share_icon_url = #{record.wxShareIconUrl,jdbcType=VARCHAR},
      </if>
      <if test="record.status != null">
        status = #{record.status,jdbcType=SMALLINT},
      </if>
      <if test="record.createTime != null">
        create_time = #{record.createTime,jdbcType=TIMESTAMP},
      </if>
      <if test="record.updateTime != null">
        update_time = #{record.updateTime,jdbcType=TIMESTAMP},
      </if>
    </set>
    <if test="_parameter != null">
      <include refid="Update_By_Example_Where_Clause" />
    </if>
  </update>
  <update id="updateByExample" parameterType="map">
    <!--
      WARNING - @mbggenerated
      This element is automatically generated by MyBatis Generator, do not modify.
      This element was generated on Tue Jan 13 16:05:27 CST 2015.
    -->
    update tb_product
    set id = #{record.id,jdbcType=INTEGER},
      sku_category_id = #{record.skuCategoryId,jdbcType=INTEGER},
      category_id = #{record.categoryId,jdbcType=INTEGER},
      out_id = #{record.outId,jdbcType=VARCHAR},
      name = #{record.name,jdbcType=VARCHAR},
      description = #{record.description,jdbcType=VARCHAR},
      param = #{record.param,jdbcType=VARCHAR},
      stock = #{record.stock,jdbcType=INTEGER},
      origin_price = #{record.originPrice,jdbcType=DOUBLE},
      price = #{record.price,jdbcType=DOUBLE},
      cover_pic_url = #{record.coverPicUrl,jdbcType=VARCHAR},
      wx_share_title = #{record.wxShareTitle,jdbcType=VARCHAR},
      wx_share_content = #{record.wxShareContent,jdbcType=VARCHAR},
      wx_share_icon_url = #{record.wxShareIconUrl,jdbcType=VARCHAR},
      status = #{record.status,jdbcType=SMALLINT},
      create_time = #{record.createTime,jdbcType=TIMESTAMP},
      update_time = #{record.updateTime,jdbcType=TIMESTAMP}
    <if test="_parameter != null">
      <include refid="Update_By_Example_Where_Clause" />
    </if>
  </update>
  <update id="updateByPrimaryKeySelective" parameterType="com.bruce.geekway.model.Product">
    <!--
      WARNING - @mbggenerated
      This element is automatically generated by MyBatis Generator, do not modify.
      This element was generated on Tue Jan 13 16:05:27 CST 2015.
    -->
    update tb_product
    <set>
      <if test="skuCategoryId != null">
        sku_category_id = #{skuCategoryId,jdbcType=INTEGER},
      </if>
      <if test="categoryId != null">
        category_id = #{categoryId,jdbcType=INTEGER},
      </if>
      <if test="outId != null">
        out_id = #{outId,jdbcType=VARCHAR},
      </if>
      <if test="name != null">
        name = #{name,jdbcType=VARCHAR},
      </if>
      <if test="description != null">
        description = #{description,jdbcType=VARCHAR},
      </if>
      <if test="param != null">
        param = #{param,jdbcType=VARCHAR},
      </if>
      <if test="stock != null">
        stock = #{stock,jdbcType=INTEGER},
      </if>
      <if test="originPrice != null">
        origin_price = #{originPrice,jdbcType=DOUBLE},
      </if>
      <if test="price != null">
        price = #{price,jdbcType=DOUBLE},
      </if>
      <if test="coverPicUrl != null">
        cover_pic_url = #{coverPicUrl,jdbcType=VARCHAR},
      </if>
      <if test="wxShareTitle != null">
        wx_share_title = #{wxShareTitle,jdbcType=VARCHAR},
      </if>
      <if test="wxShareContent != null">
        wx_share_content = #{wxShareContent,jdbcType=VARCHAR},
      </if>
      <if test="wxShareIconUrl != null">
        wx_share_icon_url = #{wxShareIconUrl,jdbcType=VARCHAR},
      </if>
      <if test="status != null">
        status = #{status,jdbcType=SMALLINT},
      </if>
      <if test="createTime != null">
        create_time = #{createTime,jdbcType=TIMESTAMP},
      </if>
      <if test="updateTime != null">
        update_time = #{updateTime,jdbcType=TIMESTAMP},
      </if>
    </set>
    where id = #{id,jdbcType=INTEGER}
  </update>
  <update id="updateByPrimaryKey" parameterType="com.bruce.geekway.model.Product">
    <!--
      WARNING - @mbggenerated
      This element is automatically generated by MyBatis Generator, do not modify.
      This element was generated on Tue Jan 13 16:05:27 CST 2015.
    -->
    update tb_product
    set sku_category_id = #{skuCategoryId,jdbcType=INTEGER},
      category_id = #{categoryId,jdbcType=INTEGER},
      out_id = #{outId,jdbcType=VARCHAR},
      name = #{name,jdbcType=VARCHAR},
      description = #{description,jdbcType=VARCHAR},
      param = #{param,jdbcType=VARCHAR},
      stock = #{stock,jdbcType=INTEGER},
      origin_price = #{originPrice,jdbcType=DOUBLE},
      price = #{price,jdbcType=DOUBLE},
      cover_pic_url = #{coverPicUrl,jdbcType=VARCHAR},
      wx_share_title = #{wxShareTitle,jdbcType=VARCHAR},
      wx_share_content = #{wxShareContent,jdbcType=VARCHAR},
      wx_share_icon_url = #{wxShareIconUrl,jdbcType=VARCHAR},
      status = #{status,jdbcType=SMALLINT},
      create_time = #{createTime,jdbcType=TIMESTAMP},
      update_time = #{updateTime,jdbcType=TIMESTAMP}
    where id = #{id,jdbcType=INTEGER}
  </update>
</mapper>